{
    "@class": "com.kony.gen.viz.model.container.KVizScrollFlexForm",
    "DNDConfig": null,
    "_margin_": [
        0,
        0,
        0,
        0
    ],
    "_padding_": [
        0,
        0,
        0,
        0
    ],
    "_skin_": "se222133c312470483c74bb6e60f2088",
    "_title_": null,
    "addWidgetsdone": false,
    "allboxes": [],
    "android": {
        "needAppMenu": false
    },
    "canUpdateUI": true,
    "children": [
        "flxMasterContainer"
    ],
    "containerweight": 100,
    "currentLocale": null,
    "desktopweb": {
        "needAppMenu": false
    },
    "device": "iPhone6",
    "displayorientation": 1,
    "enabled": false,
    "enabledforidletimeout": false,
    "id": "frmMovieStyleImage",
    "info": null,
    "initdone": false,
    "inputaccessoryviewtype": 4,
    "ipad": {
        "psp": {
            "inputAccessoryViewType": 4
        }
    },
    "iphone": {
        "needAppMenu": false,
        "psp": {
            "inputAccessoryViewType": 4,
            "titleBarConfig": {
                "buttonClosureLeftSideView": "",
                "buttonClosureRightSideView": "",
                "buttonText": "Edit",
                "leftButtonText": "Back",
                "leftTitle": "Back",
                "prevFormTitle": false,
                "renderTitleText": true,
                "rightTitle": "Edit",
                "titleBarLeftSideView": "button",
                "titleBarRightSideView": "button",
                "titleClosureLeftSideView": "",
                "titleClosureRightSideView": "",
                "visible": false
            }
        },
        "titleBar": false
    },
    "isvisible": true,
    "kuid": "9d7ca9be61ea4a4fae18cc53ff3037d4",
    "layouttype": 2,
    "name": "kony.ui.Form2",
    "needappmenu": true,
    "orientation": 1,
    "paddinginpixel": false,
    "percent": true,
    "platform": "iphone",
    "postshow": "AS_Form_6e2950bed09e4bbdbf7b28f970995d78",
    "prevDevice": "iPhone6",
    "prevPlatform": "iphone",
    "retainscrollposition": false,
    "shellCSS": "iOS_iPhone6",
    "snapgridsize": 10,
    "snaptogrid": true,
    "spaan": {
        "needAppMenu": false
    },
    "spabb": {
        "needAppMenu": false
    },
    "spaip": {
        "needAppMenu": false
    },
    "spawinphone8": {
        "needAppMenu": false
    },
    "titleBarSkin": "s774cfe445934a929438e8efd7286ada",
    "titlebar": true,
    "type": 3,
    "wType": "Form",
    "winphone8": {
        "needAppMenu": false
    }
}